larq_zoo/__init__.py
larq_zoo/core/__init__.py
larq_zoo/core/model_factory.py
larq_zoo/core/utils.py
larq_zoo/literature/__init__.py
larq_zoo/literature/binary_alex_net.py
larq_zoo/literature/birealnet.py
larq_zoo/literature/densenet.py
larq_zoo/literature/dorefanet.py
larq_zoo/literature/meliusnet.py
larq_zoo/literature/real_to_bin_nets.py
larq_zoo/literature/resnet_e.py
larq_zoo/literature/xnornet.py
larq_zoo/sota/__init__.py
larq_zoo/sota/quicknet.py
larq_zoo/training/__init__.py
larq_zoo/training/basic_experiments.py
larq_zoo/training/data.py
larq_zoo/training/datasets.py
larq_zoo/training/learning_schedules.py
larq_zoo/training/main.py
larq_zoo/training/multi_stage_experiments.py
larq_zoo/training/sota_experiments.py
larq_zoo/training/train.py
larq_zoo/training/knowledge_distillation/__init__.py
larq_zoo/training/knowledge_distillation/knowledge_distillation.py
larq_zoo/training/knowledge_distillation/multi_stage_training.py
larq_zoo-2.3.3.dist-info/licenses/LICENSE
tests/__init__.py
tests/data_test.py
tests/models_test.py
tests/train_test.py
tests/utils_test.py
tests/version_test.py
larq_zoo-2.3.3.dist-info/METADATA
larq_zoo-2.3.3.dist-info/WHEEL
larq_zoo-2.3.3.dist-info/entry_points.txt
larq_zoo-2.3.3.dist-info/top_level.txt
larq_zoo-2.3.3.dist-info/RECORD
