Metadata-Version: 2.4
Name: larq-zoo
Version: 2.3.3
Summary: Reference implementations of popular Binarized Neural Networks
Home-page: https://github.com/plumerai/larq-zoo
Author: Plumerai
Author-email: opensource@plumerai.com
License: Apache 2.0
Classifier: Development Status :: 2 - Pre-Alpha
Classifier: Intended Audience :: Developers
Classifier: Intended Audience :: Education
Classifier: Intended Audience :: Science/Research
Classifier: License :: OSI Approved :: Apache Software License
Classifier: Programming Language :: Python :: 3
Classifier: Programming Language :: Python :: 3 :: Only
Classifier: Programming Language :: Python :: 3.9
Classifier: Programming Language :: Python :: 3.10
Classifier: Topic :: Scientific/Engineering
Classifier: Topic :: Scientific/Engineering :: Mathematics
Classifier: Topic :: Scientific/Engineering :: Artificial Intelligence
Classifier: Topic :: Software Development
License-File: LICENSE
Requires-Dist: numpy>=1.15.0
Requires-Dist: packaging>=19
Requires-Dist: larq<0.13.2,>=0.9.2
Requires-Dist: zookeeper>=1.0.0
Requires-Dist: typeguard<3.0.0
Requires-Dist: protobuf<3.21
Provides-Extra: tensorflow
Requires-Dist: tensorflow>=2.4.0; extra == "tensorflow"
Provides-Extra: tensorflow-gpu
Requires-Dist: tensorflow-gpu>=2.4.0; extra == "tensorflow-gpu"
Provides-Extra: test
Requires-Dist: black==25.1.0; extra == "test"
Requires-Dist: dill==0.4.0; extra == "test"
Requires-Dist: flake8==7.1.2; extra == "test"
Requires-Dist: isort==6.0.0; extra == "test"
Requires-Dist: pytype==2024.9.13; extra == "test"
Requires-Dist: pytest==8.3.5; extra == "test"
Requires-Dist: pytest-cov==6.1.1; extra == "test"
Requires-Dist: pytest-mock==3.14.0; extra == "test"
Requires-Dist: pytest-xdist==3.6.1; extra == "test"
Requires-Dist: Pillow==11.2.1; extra == "test"
Requires-Dist: tensorflow_datasets>=3.1.0; extra == "test"
Dynamic: author
Dynamic: author-email
Dynamic: classifier
Dynamic: description
Dynamic: description-content-type
Dynamic: home-page
Dynamic: license
Dynamic: license-file
Dynamic: provides-extra
Dynamic: requires-dist
Dynamic: summary
